odoo/addons/stock_inventory_cost_info/README.rst
odoo/addons/stock_inventory_cost_info/__init__.py
odoo/addons/stock_inventory_cost_info/__manifest__.py
odoo/addons/stock_inventory_cost_info/hooks.py
odoo/addons/stock_inventory_cost_info/i18n/es.po
odoo/addons/stock_inventory_cost_info/i18n/it.po
odoo/addons/stock_inventory_cost_info/i18n/stock_inventory_cost_info.pot
odoo/addons/stock_inventory_cost_info/models/__init__.py
odoo/addons/stock_inventory_cost_info/models/stock_inventory.py
odoo/addons/stock_inventory_cost_info/readme/CONTRIBUTORS.rst
odoo/addons/stock_inventory_cost_info/readme/DESCRIPTION.rst
odoo/addons/stock_inventory_cost_info/readme/INSTALL.rst
odoo/addons/stock_inventory_cost_info/readme/USAGE.rst
odoo/addons/stock_inventory_cost_info/static/description/icon.png
odoo/addons/stock_inventory_cost_info/static/description/index.html
odoo/addons/stock_inventory_cost_info/tests/__init__.py
odoo/addons/stock_inventory_cost_info/tests/test_stock_inventory_cost_info.py
odoo/addons/stock_inventory_cost_info/views/report_stockinventory.xml
odoo/addons/stock_inventory_cost_info/views/stock_inventory_views.xml
odoo14_addon_stock_inventory_cost_info-14.0.1.0.1.dev7.dist-info/METADATA
odoo14_addon_stock_inventory_cost_info-14.0.1.0.1.dev7.dist-info/WHEEL
odoo14_addon_stock_inventory_cost_info-14.0.1.0.1.dev7.dist-info/top_level.txt
odoo14_addon_stock_inventory_cost_info-14.0.1.0.1.dev7.dist-info/RECORD
